foliant/backends/slate.py
foliantcontrib.slate-1.0.8.dist-info/LICENSE
foliantcontrib.slate-1.0.8.dist-info/METADATA
foliantcontrib.slate-1.0.8.dist-info/WHEEL
foliantcontrib.slate-1.0.8.dist-info/top_level.txt
foliantcontrib.slate-1.0.8.dist-info/RECORD
