Metadata-Version: 2.1
Name: foliantcontrib.slate
Version: 1.0.8
Summary: Slate backend for Foliant documentation generator.
Home-page: https://github.com/foliant-docs/foliantcontrib.slate
Author: Daniil Minukhin
Author-email: ddddsa@gmail.com
License: MIT
Platform: any
Classifier: Development Status :: 5 - Production/Stable
Classifier: Environment :: Console
Classifier: Intended Audience :: Developers
Classifier: License :: OSI Approved :: MIT License
Classifier: Operating System :: OS Independent
Classifier: Programming Language :: Python
Classifier: Topic :: Documentation
Classifier: Topic :: Utilities
Requires-Dist: foliant (>=1.0.8)
Requires-Dist: PyYAML
Requires-Dist: foliantcontrib.meta (>=1.3.0)
